<edmx:Edmx xmlns:edmx="http://docs.oasis-open.org/odata/ns/edmx" Version="4.0">
    <edmx:Reference Uri="/sap/opu/odata/IWFND/CATALOGSERVICE;v=2/Vocabularies(TechnicalName='%2FIWBEP%2FVOC_COMMON',Version='0001',SAP__Origin='LOCAL')/$value">
        <edmx:Include Namespace="com.sap.vocabularies.Common.v1" Alias="Common" />
    </edmx:Reference>
    <edmx:Reference Uri="/sap/opu/odata/IWFND/CATALOGSERVICE;v=2/Vocabularies(TechnicalName='%2FIWBEP%2FVOC_UI',Version='0001',SAP__Origin='LOCAL')/$value">
        <edmx:Include Namespace="com.sap.vocabularies.UI.v1" Alias="UI" />
    </edmx:Reference>
    <edmx:Reference Uri="/sap/opu/odata/IWFND/CATALOGSERVICE;v=2/Vocabularies(TechnicalName='%2FIWBEP%2FVOC_COMMUNICATION',Version='0001',SAP__Origin='LOCAL')/$value">
        <edmx:Include Namespace="com.sap.vocabularies.Communication.v1" Alias="Communication" />
    </edmx:Reference>
    <edmx:Reference Uri="/odata/v2/rfq/$metadata">
        <edmx:Include Namespace="RFQService" Alias="SAP" />
    </edmx:Reference>
    <edmx:DataServices>
        <Schema xmlns="http://docs.oasis-open.org/odata/ns/edm" Namespace="local">
            <Annotations Target="SAP.RFQHeaders">
                <Annotation Term="UI.SelectionFields">
                    <Collection>
                        <PropertyPath>RfqNumber</PropertyPath>
                        <PropertyPath>Status</PropertyPath>
                    </Collection>
                </Annotation>
                <Annotation Term="UI.LineItem">
                    <Collection>
                        <Record Type="UI.DataField">
                            <PropertyValue Property="Value" Path="RfqNumber" />
                            <PropertyValue Property="Label" String="RFQ Number" />
                        </Record>
                    </Collection>
                </Annotation>
            </Annotations>

            <Annotations Target="SAP.RFQHeaders/RfqNumber">
                <Annotation Term="Common.Label" String="RFQ Number" />
                <Annotation Term="Common.ValueList">
                    <Record Type="Common.ValueListType">
                        <PropertyValue Property="CollectionPath" String="RFQHeaders" />
                        <PropertyValue Property="SearchSupported" Bool="true" />
                        <PropertyValue Property="Parameters">
                            <Collection>
                                <Record Type="Common.ValueListParameterInOut">
                                    <PropertyValue Property="LocalDataProperty" PropertyPath="RfqNumber" />
                                    <PropertyValue Property="ValueListProperty" String="RfqNumber" />
                                </Record>
                            </Collection>
                        </PropertyValue>
                    </Record>
                </Annotation>
            </Annotations>

            <Annotations Target="SAP.ZC_RFQBasicDetails/Waers">
                <Annotation Term="Common.ValueList">
                    <Record Type="Common.ValueListType">
                        <PropertyValue Property="CollectionPath" String="ZC_AISP_CURRENCY_VH" />
                        <PropertyValue Property="SearchSupported" Bool="true" />
                        <PropertyValue Property="Parameters">
                            <Collection>
                                <Record Type="Common.ValueListParameterInOut">
                                    <PropertyValue Property="LocalDataProperty" PropertyPath="Waers" />
                                    <PropertyValue Property="ValueListProperty" String="Waers" />
                                </Record>
                                <Record Type="Common.ValueListParameterDisplayOnly">
                                    <PropertyValue Property="ValueListProperty" String="Ltext" />
                                </Record>
                            </Collection>
                        </PropertyValue>
                    </Record>
                </Annotation>
            </Annotations>

            <Annotations Target="SAP.ZC_RFQBasicDetails/Zterm">
                <Annotation Term="Common.ValueList">
                    <Record Type="Common.ValueListType">
                        <PropertyValue Property="CollectionPath" String="ZC_AISP_PAYMENTTERMS_VH" />
                        <PropertyValue Property="SearchSupported" Bool="true" />
                        <PropertyValue Property="Parameters">
                            <Collection>
                                <Record Type="Common.ValueListParameterInOut">
                                    <PropertyValue Property="LocalDataProperty" PropertyPath="Zterm" />
                                    <PropertyValue Property="ValueListProperty" String="Zterm" />
                                </Record>
                                <Record Type="Common.ValueListParameterDisplayOnly">
                                    <PropertyValue Property="ValueListProperty" String="Vtext" />
                                </Record>
                            </Collection>
                        </PropertyValue>
                    </Record>
                </Annotation>
            </Annotations>

            <Annotations Target="SAP.ZC_RFQBasicDetails/Inco1">
                <Annotation Term="Common.ValueList">
                    <Record Type="Common.ValueListType">
                        <PropertyValue Property="CollectionPath" String="ZC_AISP_INCOTERMS_VH" />
                        <PropertyValue Property="SearchSupported" Bool="true" />
                        <PropertyValue Property="Parameters">
                            <Collection>
                                <Record Type="Common.ValueListParameterInOut">
                                    <PropertyValue Property="LocalDataProperty" PropertyPath="Inco1" />
                                    <PropertyValue Property="ValueListProperty" String="Inco1" />
                                </Record>
                                <Record Type="Common.ValueListParameterDisplayOnly">
                                    <PropertyValue Property="ValueListProperty" String="Bezei" />
                                </Record>
                            </Collection>
                        </PropertyValue>
                    </Record>
                </Annotation>
            </Annotations>

            <Annotations Target="SAP.ZC_RFQBasicDetails/CompanyCode">
                <Annotation Term="Common.ValueList">
                    <Record Type="Common.ValueListType">
                        <PropertyValue Property="CollectionPath" String="ZC_AISP_COMPANYCODE_VH" />
                        <PropertyValue Property="SearchSupported" Bool="true" />
                        <PropertyValue Property="Parameters">
                            <Collection>
                                <Record Type="Common.ValueListParameterInOut">
                                    <PropertyValue Property="LocalDataProperty" PropertyPath="CompanyCode" />
                                    <PropertyValue Property="ValueListProperty" String="CompanyCode" />
                                </Record>
                                <Record Type="Common.ValueListParameterDisplayOnly">
                                    <PropertyValue Property="ValueListProperty" String="Description" />
                                </Record>
                            </Collection>
                        </PropertyValue>
                    </Record>
                </Annotation>
            </Annotations>

            <Annotations Target="SAP.ZC_RFQBasicDetails/Ekorg">
                <Annotation Term="Common.ValueList">
                    <Record Type="Common.ValueListType">
                        <PropertyValue Property="CollectionPath" String="ZC_AISP_PURCHASEORG_VH" />
                        <PropertyValue Property="SearchSupported" Bool="true" />
                        <PropertyValue Property="Parameters">
                            <Collection>
                                <Record Type="Common.ValueListParameterInOut">
                                    <PropertyValue Property="LocalDataProperty" PropertyPath="Ekorg" />
                                    <PropertyValue Property="ValueListProperty" String="Ekorg" />
                                </Record>
                                <Record Type="Common.ValueListParameterDisplayOnly">
                                    <PropertyValue Property="ValueListProperty" String="Ekotx" />
                                </Record>
                            </Collection>
                        </PropertyValue>
                    </Record>
                </Annotation>
            </Annotations>

            <Annotations Target="SAP.ZC_RFQBasicDetails/Ekgrp">
                <Annotation Term="Common.ValueList">
                    <Record Type="Common.ValueListType">
                        <PropertyValue Property="CollectionPath" String="ZC_AISP_PURCHASEGROUP_VH" />
                        <PropertyValue Property="SearchSupported" Bool="true" />
                        <PropertyValue Property="Parameters">
                            <Collection>
                                <Record Type="Common.ValueListParameterInOut">
                                    <PropertyValue Property="LocalDataProperty" PropertyPath="Ekgrp" />
                                    <PropertyValue Property="ValueListProperty" String="Ekgrp" />
                                </Record>
                                <Record Type="Common.ValueListParameterDisplayOnly">
                                    <PropertyValue Property="ValueListProperty" String="Eknam" />
                                </Record>
                            </Collection>
                        </PropertyValue>
                    </Record>
                </Annotation>
            </Annotations>

            <Annotations Target="SAP.ZC_RFQItemDetails/Description">
                <Annotation Term="Common.ValueList">
                    <Record Type="Common.ValueListType">
                        <PropertyValue Property="CollectionPath" String="ZC_AISP_MATERIALDETAILS_VH" />
                        <PropertyValue Property="SearchSupported" Bool="true" />
                        <PropertyValue Property="Parameters">
                            <Collection>
                                <Record Type="Common.ValueListParameterInOut">
                                    <PropertyValue Property="LocalDataProperty" PropertyPath="Matnr" />
                                    <PropertyValue Property="ValueListProperty" String="Matnr" />
                                </Record>
                                <Record Type="Common.ValueListParameterInOut">
                                    <PropertyValue Property="LocalDataProperty" PropertyPath="Description" />
                                    <PropertyValue Property="ValueListProperty" String="Description" />
                                </Record>
                                <Record Type="Common.ValueListParameterInOut">
                                    <PropertyValue Property="LocalDataProperty" PropertyPath="Maktx" />
                                    <PropertyValue Property="ValueListProperty" String="Maktx" />
                                </Record>
                                <Record Type="Common.ValueListParameterOut">
                                    <PropertyValue Property="LocalDataProperty" PropertyPath="UnitOfMeasure" />
                                    <PropertyValue Property="ValueListProperty" String="UnitOfMeasure" />
                                </Record>
                            </Collection>
                        </PropertyValue>
                    </Record>
                </Annotation>
            </Annotations>

            <Annotations Target="SAP.ZC_RFQItemDetails/Werks">
                <Annotation Term="Common.ValueList">
                    <Record Type="Common.ValueListType">
                        <PropertyValue Property="CollectionPath" String="ZC_AISP_PLANT_VH" />
                        <PropertyValue Property="SearchSupported" Bool="true" />
                        <PropertyValue Property="Parameters">
                            <Collection>
                                <Record Type="Common.ValueListParameterInOut">
                                    <PropertyValue Property="LocalDataProperty" PropertyPath="Werks" />
                                    <PropertyValue Property="ValueListProperty" String="Werks" />
                                </Record>
                                <Record Type="Common.ValueListParameterDisplayOnly">
                                    <PropertyValue Property="ValueListProperty" String="Name1" />
                                </Record>
                            </Collection>
                        </PropertyValue>
                    </Record>
                </Annotation>
            </Annotations>

            <Annotations Target="SAP.ZC_RFQSupplierDetails/Lifnr">
                <Annotation Term="Common.ValueList">
                    <Record Type="Common.ValueListType">
                        <PropertyValue Property="CollectionPath" String="ZC_AISP_VENDORDETAILS_VH" />
                        <PropertyValue Property="SearchSupported" Bool="true" />
                        <PropertyValue Property="Parameters">
                            <Collection>
                                <Record Type="Common.ValueListParameterInOut">
                                    <PropertyValue Property="LocalDataProperty" PropertyPath="Lifnr" />
                                    <PropertyValue Property="ValueListProperty" String="Lifnr" />
                                </Record>
                                <Record Type="Common.ValueListParameterDisplayOnly">
                                    <PropertyValue Property="ValueListProperty" String="VendorName" />
                                </Record>
                            </Collection>
                        </PropertyValue>
                    </Record>
                </Annotation>
            </Annotations>

            <Annotations Target="SAP.RFQHeaders/Status">
                <Annotation Term="Common.ValueListWithFixedValues"  Bool="true"/>
                <Annotation Term="Common.ValueList">
                    <Record Type="Common.ValueListType">
                        <PropertyValue Property="CollectionPath" String="Status_VH"/>
                        <PropertyValue Property="DistinctValuesSupported" Bool="true"/>
                        <PropertyValue Property="SearchSupported" Bool="true"/>
                        <PropertyValue Property="Parameters">
                            <Collection>
                                <Record Type="Common.ValueListParameterInOut">
                                    <PropertyValue Property="LocalDataProperty" PropertyPath="Status"/>
                                    <PropertyValue Property="ValueListProperty" String="StatusText"/>
                                </Record>
                            </Collection>
                        </PropertyValue>
                    </Record>
                </Annotation>
            </Annotations>
        </Schema>
    </edmx:DataServices>
</edmx:Edmx>
